sqlconfig/__init__.py
sqlconfig/__main__.py
sqlconfig/cli.py
sqlconfig/lib.py
sqlconfig-0.1.dist-info/LICENSE.txt
sqlconfig-0.1.dist-info/METADATA
sqlconfig-0.1.dist-info/WHEEL
sqlconfig-0.1.dist-info/entry_points.txt
sqlconfig-0.1.dist-info/top_level.txt
sqlconfig-0.1.dist-info/RECORD
