Metadata-Version: 2.1
Name: sqlconfig
Version: 0.1
Summary: Use SQLite to manage your configs
Home-page: https://github.com/petehunt/sqlconfig
Author: Pete Hunt
Author-email: floydophone@gmail.com
License: MIT
Platform: UNKNOWN
Classifier: Development Status :: 3 - Alpha
Classifier: License :: OSI Approved :: MIT License
Classifier: Programming Language :: Python :: 3
Classifier: Topic :: Database
Requires-Python: >=3
